{
  "status": "PROTOTYPE",
  "prototype_warning": "This is not canonical learner_state.json.",
  "reducer_version": "ULGA-S9Z6-prototype",
  "learner_ids": [
    "learner:usr_001"
  ],
  "node_count": 5,
  "nodes": [
    {
      "learner_id": "learner:usr_001",
      "node_id": "grammar:EGP_000142",
      "node_type": "grammar",
      "exposure": {
        "count": 6,
        "first_seen_at": "2026-06-18T10:01:00Z",
        "last_seen_at": "2026-06-18T10:07:00Z",
        "source_types": [
          "assessment",
          "exercise"
        ],
        "passive_count": 0,
        "active_count": 6
      },
      "practice": {
        "attempt_count": 2,
        "first_try_correct_count": 1,
        "retry_count": 1,
        "hint_count": 1,
        "correct_count": 1,
        "incorrect_count": 1,
        "response_time_total_ms": 3400,
        "average_response_time_ms": 1700.0,
        "latest_practice_at": "2026-06-18T10:04:00Z",
        "success_rate": 0.5
      },
      "assessment": {
        "attempt_count": 3,
        "score_total": 2.0,
        "max_score_total": 3.0,
        "success_rate": 0.6667,
        "latest_assessment_at": "2026-06-18T10:07:00Z",
        "retention_check_pass_count": 1,
        "retention_check_fail_count": 1
      },
      "reinforcement": {
        "hint_count": 1,
        "retry_count": 1,
        "incorrect_count": 1,
        "weak_node_signal_count": 3,
        "reinforcement_need_score": 0.6
      },
      "engagement": {
        "practice_started_count": 0,
        "practice_completed_count": 0,
        "content_completed_count": 0
      },
      "mastery_projection": {
        "raw_score": 0.455,
        "band": "review_needed",
        "confidence": "high"
      }
    },
    {
      "learner_id": "learner:usr_001",
      "node_id": "pattern:PATTERN_NODE_000014",
      "node_type": "pattern",
      "exposure": {
        "count": 6,
        "first_seen_at": "2026-06-18T10:01:00Z",
        "last_seen_at": "2026-06-18T10:07:00Z",
        "source_types": [
          "assessment",
          "exercise"
        ],
        "passive_count": 0,
        "active_count": 6
      },
      "practice": {
        "attempt_count": 2,
        "first_try_correct_count": 1,
        "retry_count": 1,
        "hint_count": 1,
        "correct_count": 1,
        "incorrect_count": 1,
        "response_time_total_ms": 3400,
        "average_response_time_ms": 1700.0,
        "latest_practice_at": "2026-06-18T10:04:00Z",
        "success_rate": 0.5
      },
      "assessment": {
        "attempt_count": 3,
        "score_total": 2.0,
        "max_score_total": 3.0,
        "success_rate": 0.6667,
        "latest_assessment_at": "2026-06-18T10:07:00Z",
        "retention_check_pass_count": 1,
        "retention_check_fail_count": 1
      },
      "reinforcement": {
        "hint_count": 1,
        "retry_count": 1,
        "incorrect_count": 1,
        "weak_node_signal_count": 3,
        "reinforcement_need_score": 0.6
      },
      "engagement": {
        "practice_started_count": 0,
        "practice_completed_count": 0,
        "content_completed_count": 0
      },
      "mastery_projection": {
        "raw_score": 0.455,
        "band": "review_needed",
        "confidence": "high"
      }
    },
    {
      "learner_id": "learner:usr_001",
      "node_id": "theme:a1_food_and_drink",
      "node_type": "theme",
      "exposure": {
        "count": 8,
        "first_seen_at": "2026-06-18T10:00:00Z",
        "last_seen_at": "2026-06-18T10:08:00Z",
        "source_types": [
          "assessment",
          "exercise",
          "reading"
        ],
        "passive_count": 1,
        "active_count": 7
      },
      "practice": {
        "attempt_count": 2,
        "first_try_correct_count": 1,
        "retry_count": 1,
        "hint_count": 1,
        "correct_count": 1,
        "incorrect_count": 1,
        "response_time_total_ms": 3400,
        "average_response_time_ms": 1700.0,
        "latest_practice_at": "2026-06-18T10:04:00Z",
        "success_rate": 0.5
      },
      "assessment": {
        "attempt_count": 3,
        "score_total": 2.0,
        "max_score_total": 3.0,
        "success_rate": 0.6667,
        "latest_assessment_at": "2026-06-18T10:07:00Z",
        "retention_check_pass_count": 1,
        "retention_check_fail_count": 1
      },
      "reinforcement": {
        "hint_count": 1,
        "retry_count": 1,
        "incorrect_count": 1,
        "weak_node_signal_count": 3,
        "reinforcement_need_score": 0.6
      },
      "engagement": {
        "practice_started_count": 0,
        "practice_completed_count": 0,
        "content_completed_count": 1
      },
      "mastery_projection": {
        "raw_score": 0.0,
        "band": "seen",
        "confidence": "high"
      }
    },
    {
      "learner_id": "learner:usr_001",
      "node_id": "vocab:apple",
      "node_type": "vocabulary",
      "exposure": {
        "count": 1,
        "first_seen_at": "2026-06-18T10:00:00Z",
        "last_seen_at": "2026-06-18T10:00:00Z",
        "source_types": [
          "reading"
        ],
        "passive_count": 1,
        "active_count": 0
      },
      "practice": {
        "attempt_count": 0,
        "first_try_correct_count": 0,
        "retry_count": 0,
        "hint_count": 0,
        "correct_count": 0,
        "incorrect_count": 0,
        "response_time_total_ms": 0,
        "average_response_time_ms": null,
        "latest_practice_at": null,
        "success_rate": null
      },
      "assessment": {
        "attempt_count": 0,
        "score_total": 0.0,
        "max_score_total": 0.0,
        "success_rate": null,
        "latest_assessment_at": null,
        "retention_check_pass_count": 0,
        "retention_check_fail_count": 0
      },
      "reinforcement": {
        "hint_count": 0,
        "retry_count": 0,
        "incorrect_count": 0,
        "weak_node_signal_count": 0,
        "reinforcement_need_score": 0.0
      },
      "engagement": {
        "practice_started_count": 0,
        "practice_completed_count": 0,
        "content_completed_count": 0
      },
      "mastery_projection": {
        "raw_score": 0.0333,
        "band": "seen",
        "confidence": "low"
      }
    },
    {
      "learner_id": "learner:usr_001",
      "node_id": "vocab:banana",
      "node_type": "vocabulary",
      "exposure": {
        "count": 6,
        "first_seen_at": "2026-06-18T10:01:00Z",
        "last_seen_at": "2026-06-18T10:07:00Z",
        "source_types": [
          "assessment",
          "exercise"
        ],
        "passive_count": 0,
        "active_count": 6
      },
      "practice": {
        "attempt_count": 2,
        "first_try_correct_count": 1,
        "retry_count": 1,
        "hint_count": 1,
        "correct_count": 1,
        "incorrect_count": 1,
        "response_time_total_ms": 3400,
        "average_response_time_ms": 1700.0,
        "latest_practice_at": "2026-06-18T10:04:00Z",
        "success_rate": 0.5
      },
      "assessment": {
        "attempt_count": 3,
        "score_total": 2.0,
        "max_score_total": 3.0,
        "success_rate": 0.6667,
        "latest_assessment_at": "2026-06-18T10:07:00Z",
        "retention_check_pass_count": 1,
        "retention_check_fail_count": 1
      },
      "reinforcement": {
        "hint_count": 1,
        "retry_count": 1,
        "incorrect_count": 1,
        "weak_node_signal_count": 3,
        "reinforcement_need_score": 0.6
      },
      "engagement": {
        "practice_started_count": 0,
        "practice_completed_count": 0,
        "content_completed_count": 0
      },
      "mastery_projection": {
        "raw_score": 0.455,
        "band": "review_needed",
        "confidence": "high"
      }
    }
  ]
}
